mse_cli/__init__.py
mse_cli/color.py
mse_cli/error.py
mse_cli/log.py
mse_cli/main.py
mse_cli/cloud/__init__.py
mse_cli/cloud/api/__init__.py
mse_cli/cloud/api/app.py
mse_cli/cloud/api/auth.py
mse_cli/cloud/api/hardware.py
mse_cli/cloud/api/project.py
mse_cli/cloud/api/types.py
mse_cli/cloud/api/user.py
mse_cli/cloud/command/__init__.py
mse_cli/cloud/command/context.py
mse_cli/cloud/command/deploy.py
mse_cli/cloud/command/helpers.py
mse_cli/cloud/command/init.py
mse_cli/cloud/command/list_all.py
mse_cli/cloud/command/localtest.py
mse_cli/cloud/command/login.py
mse_cli/cloud/command/logout.py
mse_cli/cloud/command/logs.py
mse_cli/cloud/command/scaffold.py
mse_cli/cloud/command/status.py
mse_cli/cloud/command/stop.py
mse_cli/cloud/command/test.py
mse_cli/cloud/command/verify.py
mse_cli/cloud/model/__init__.py
mse_cli/cloud/model/context.py
mse_cli/cloud/model/user.py
mse_cli/common/__init__.py
mse_cli/common/helpers.py
mse_cli/core/__init__.py
mse_cli/core/base64.py
mse_cli/core/bootstrap.py
mse_cli/core/clock_tick.py
mse_cli/core/conf.py
mse_cli/core/enclave.py
mse_cli/core/fs.py
mse_cli/core/ignore_file.py
mse_cli/core/no_sgx_docker.py
mse_cli/core/sgx_docker.py
mse_cli/core/spinner.py
mse_cli/core/test_docker.py
mse_cli/home/__init__.py
mse_cli/home/command/__init__.py
mse_cli/home/command/helpers.py
mse_cli/home/command/code_provider/__init__.py
mse_cli/home/command/code_provider/decrypt.py
mse_cli/home/command/code_provider/encrypt.py
mse_cli/home/command/code_provider/localtest.py
mse_cli/home/command/code_provider/package.py
mse_cli/home/command/code_provider/scaffold.py
mse_cli/home/command/code_provider/seal.py
mse_cli/home/command/code_provider/unseal.py
mse_cli/home/command/code_provider/verify.py
mse_cli/home/command/sgx_operator/__init__.py
mse_cli/home/command/sgx_operator/evidence.py
mse_cli/home/command/sgx_operator/list_all.py
mse_cli/home/command/sgx_operator/logs.py
mse_cli/home/command/sgx_operator/restart.py
mse_cli-1.3.dist-info/METADATA
mse_cli-1.3.dist-info/WHEEL
mse_cli-1.3.dist-info/entry_points.txt
mse_cli-1.3.dist-info/top_level.txt
mse_cli-1.3.dist-info/RECORD
