Metadata-Version: 2.1
Name: mse-cli
Version: 1.3
Summary: Command Line Interface for Microservice Encryption
Author-email: Cosmian Tech <tech@cosmian.com>
License: MIT
Project-URL: homepage, https://cosmian.com
Project-URL: documentation, https://docs.cosmian.com
Project-URL: repository, https://github.com/Cosmian/mse-cli
Classifier: Development Status :: 5 - Production/Stable
Classifier: Environment :: Console
Classifier: License :: OSI Approved :: MIT License
Classifier: Programming Language :: Python :: 3
Classifier: Programming Language :: Python :: Implementation :: CPython
Requires-Python: >=3.8
Requires-Dist: cryptography <43.0.0,>=42.0.5
Requires-Dist: docker <8.0.0,>=7.1.0
Requires-Dist: intel-sgx-ra <3.0,>=2.2.1
Requires-Dist: jinja2 <3.1,>=3.0
Requires-Dist: mse-lib-crypto <2.0,>=1.4
Requires-Dist: pydantic <2.0.0,>=1.10.2
Requires-Dist: pyjwt <2.7.0,>=2.6.0
Requires-Dist: requests <3.0.0,>=2.31.0
Requires-Dist: toml <0.11.0,>=0.10.2
Requires-Dist: urllib3 <1.27.0,>=1.26.13
Provides-Extra: deploy
Requires-Dist: build <0.11.0,>=0.10.0 ; extra == 'deploy'
Requires-Dist: wheel <0.41.0,>=0.40.0 ; extra == 'deploy'
Provides-Extra: dev
Requires-Dist: pylint <3.0,>=2.17 ; extra == 'dev'
Requires-Dist: pycodestyle <3.0,>=2.10 ; extra == 'dev'
Requires-Dist: pydocstyle <7.0,>=6.3 ; extra == 'dev'
Requires-Dist: mypy <2.0,>=1.4 ; extra == 'dev'
Requires-Dist: black <24.0,>=23.7 ; extra == 'dev'
Requires-Dist: isort <6.0,>=5.12 ; extra == 'dev'
Requires-Dist: pytest <8.0,>=7.4 ; extra == 'dev'
Requires-Dist: flask ==2.2.0 ; extra == 'dev'
Requires-Dist: numpydoc <1.6.0,>=1.5.0 ; extra == 'dev'
Requires-Dist: sphinx <5.4.0,>=5.3.0 ; extra == 'dev'
Requires-Dist: sphinx-rtd-theme <1.2.0,>=1.1.1 ; extra == 'dev'
Requires-Dist: sphinx-mdinclude <0.6.0,>=0.5.3 ; extra == 'dev'
Requires-Dist: types-requests <2.29,>=2.28 ; extra == 'dev'
Requires-Dist: types-urllib3 <1.27,>=1.26 ; extra == 'dev'
Requires-Dist: types-toml <0.11,>=0.10 ; extra == 'dev'
Requires-Dist: types-setuptools <69.0.0,>=68.0.0 ; extra == 'dev'
